wordtangible/__init__.py
wordtangible/concrete.py
wordtangible/imageable.py
wordtangible/resources/__init__.py
wordtangible/resources/concreteness_ratings.csv
wordtangible-0.1.1.dist-info/LICENSE
wordtangible-0.1.1.dist-info/METADATA
wordtangible-0.1.1.dist-info/WHEEL
wordtangible-0.1.1.dist-info/RECORD
