Metadata-Version: 2.1
Name: wordtangible
Version: 0.1.1
Summary: Python library for word concreteness and imageability analysis.
Home-page: https://github.com/jrrobison1/wordtangible
License: MIT
Keywords: nlp,linguistics,concreteness,imageability
Author: Jason Robison
Author-email: jrrobison@protonmail.com
Requires-Python: >=3.10,<4.0
Classifier: Development Status :: 3 - Alpha
Classifier: Intended Audience :: Developers
Classifier: License :: OSI Approved :: MIT License
Classifier: Programming Language :: Python :: 3
Classifier: Programming Language :: Python :: 3.10
Classifier: Programming Language :: Python :: 3.11
Classifier: Programming Language :: Python :: 3.12
Requires-Dist: nltk (>=3.9.1,<4.0.0)
Project-URL: Repository, https://github.com/jrrobison1/wordtangible
